solar_as_judge/__init__.py
solar_as_judge-0.3.0.dist-info/METADATA
solar_as_judge-0.3.0.dist-info/WHEEL
solar_as_judge-0.3.0.dist-info/top_level.txt
solar_as_judge-0.3.0.dist-info/RECORD
