Metadata-Version: 2.1
Name: solar-as-judge
Version: 0.3.0
Summary: A tool for using SOLAR as a judge in coding competitions
Home-page: https://github.com/hunkim/solar-as-judge
Author: Sung Kim
Author-email: hunkim@gmail.com
License: MIT
Keywords: solar judge coding competition ai
Classifier: Development Status :: 3 - Alpha
Classifier: Intended Audience :: Developers
Classifier: License :: OSI Approved :: MIT License
Classifier: Programming Language :: Python :: 3
Classifier: Programming Language :: Python :: 3.7
Classifier: Programming Language :: Python :: 3.8
Classifier: Programming Language :: Python :: 3.9
Requires-Python: >=3.7
Requires-Dist: langchain >=0.3.0
Requires-Dist: langchain-upstage >=0.3.0
